{
	"name": "Event sheet 1",
	"events": [
		{
			"eventType": "variable",
			"name": "target",
			"type": "number",
			"initialValue": "1",
			"comment": "",
			"isStatic": false,
			"isConstant": false,
			"sid": 971227794842434
		},
		{
			"eventType": "variable",
			"name": "current_zoom",
			"type": "number",
			"initialValue": "1",
			"comment": "",
			"isStatic": false,
			"isConstant": false,
			"sid": 872474105493827
		},
		{
			"eventType": "block",
			"conditions": [
				{
					"id": "on-key-pressed",
					"objectClass": "Keyboard",
					"sid": 913998467499405,
					"parameters": {
						"key": 88
					}
				}
			],
			"actions": [],
			"sid": 569979673069381,
			"children": [
				{
					"eventType": "block",
					"conditions": [
						{
							"id": "key-is-down",
							"objectClass": "Keyboard",
							"sid": 443219609814088,
							"parameters": {
								"key": 39
							}
						},
						{
							"id": "key-is-down",
							"objectClass": "Keyboard",
							"sid": 214471347147708,
							"parameters": {
								"key": 38
							}
						},
						{
							"id": "compare-instance-variable",
							"objectClass": "player",
							"sid": 922350826130789,
							"disabled": true,
							"parameters": {
								"instance-variable": "direction",
								"comparison": 0,
								"value": "1"
							}
						},
						{
							"id": "is-boolean-instance-variable-set",
							"objectClass": "player",
							"sid": 993259750876974,
							"parameters": {
								"instance-variable": "isDashing"
							},
							"isInverted": true
						}
					],
					"actions": [
						{
							"callFunction": "toDashing",
							"sid": 426808029106435
						},
						{
							"id": "set-vector-y",
							"objectClass": "player",
							"sid": 591191141672961,
							"behaviorType": "Platform",
							"parameters": {
								"vector-y": "(-player.dashSpeed*0.85)"
							}
						},
						{
							"id": "set-vector-x",
							"objectClass": "player",
							"sid": 771858266867063,
							"behaviorType": "Platform",
							"parameters": {
								"vector-x": "player.dashSpeed/2"
							}
						},
						{
							"id": "wait",
							"objectClass": "System",
							"sid": 259393970940725,
							"parameters": {
								"seconds": "0.3"
							}
						},
						{
							"callFunction": "toNormal",
							"sid": 581369450515377
						}
					],
					"sid": 303054902588407
				},
				{
					"eventType": "block",
					"conditions": [
						{
							"id": "key-is-down",
							"objectClass": "Keyboard",
							"sid": 101927459125329,
							"parameters": {
								"key": 37
							}
						},
						{
							"id": "key-is-down",
							"objectClass": "Keyboard",
							"sid": 302275855280681,
							"parameters": {
								"key": 38
							}
						},
						{
							"id": "compare-instance-variable",
							"objectClass": "player",
							"sid": 247941036639895,
							"disabled": true,
							"parameters": {
								"instance-variable": "direction",
								"comparison": 0,
								"value": "1"
							}
						},
						{
							"id": "is-boolean-instance-variable-set",
							"objectClass": "player",
							"sid": 826277027006048,
							"parameters": {
								"instance-variable": "isDashing"
							},
							"isInverted": true
						}
					],
					"actions": [
						{
							"callFunction": "toDashing",
							"sid": 298794246139831
						},
						{
							"id": "set-vector-y",
							"objectClass": "player",
							"sid": 422773175186073,
							"behaviorType": "Platform",
							"parameters": {
								"vector-y": "(-player.dashSpeed*0.85)"
							}
						},
						{
							"id": "set-vector-x",
							"objectClass": "player",
							"sid": 279623552661994,
							"behaviorType": "Platform",
							"parameters": {
								"vector-x": "-player.dashSpeed/2"
							}
						},
						{
							"id": "wait",
							"objectClass": "System",
							"sid": 461577800429932,
							"parameters": {
								"seconds": "0.3"
							}
						},
						{
							"callFunction": "toNormal",
							"sid": 733307420347060
						}
					],
					"sid": 782674718621278
				},
				{
					"eventType": "block",
					"conditions": [
						{
							"id": "compare-instance-variable",
							"objectClass": "player",
							"sid": 532933516621745,
							"disabled": true,
							"parameters": {
								"instance-variable": "direction",
								"comparison": 0,
								"value": "2"
							}
						},
						{
							"id": "is-boolean-instance-variable-set",
							"objectClass": "player",
							"sid": 172218182768101,
							"parameters": {
								"instance-variable": "isDashing"
							},
							"isInverted": true
						},
						{
							"id": "key-is-down",
							"objectClass": "Keyboard",
							"sid": 775594799519329,
							"parameters": {
								"key": 39
							}
						}
					],
					"actions": [
						{
							"callFunction": "toDashing",
							"sid": 698175638843583
						},
						{
							"id": "set-vector-x",
							"objectClass": "player",
							"sid": 500820471273091,
							"behaviorType": "Platform",
							"parameters": {
								"vector-x": "player.dashSpeed"
							}
						},
						{
							"id": "wait",
							"objectClass": "System",
							"sid": 602572612310969,
							"parameters": {
								"seconds": "0.3"
							}
						},
						{
							"callFunction": "toNormal",
							"sid": 372556827226449
						}
					],
					"sid": 812074161632221
				},
				{
					"eventType": "block",
					"conditions": [
						{
							"id": "key-is-down",
							"objectClass": "Keyboard",
							"sid": 894888375652353,
							"parameters": {
								"key": 37
							}
						},
						{
							"id": "compare-instance-variable",
							"objectClass": "player",
							"sid": 620498934023796,
							"disabled": true,
							"parameters": {
								"instance-variable": "direction",
								"comparison": 0,
								"value": "0"
							}
						},
						{
							"id": "is-boolean-instance-variable-set",
							"objectClass": "player",
							"sid": 116391622228535,
							"parameters": {
								"instance-variable": "isDashing"
							},
							"isInverted": true
						}
					],
					"actions": [
						{
							"callFunction": "toDashing",
							"sid": 482402706437281
						},
						{
							"id": "set-vector-x",
							"objectClass": "player",
							"sid": 361444336552631,
							"behaviorType": "Platform",
							"parameters": {
								"vector-x": "-player.dashSpeed"
							}
						},
						{
							"id": "wait",
							"objectClass": "System",
							"sid": 412092794262590,
							"parameters": {
								"seconds": "0.3"
							}
						},
						{
							"callFunction": "toNormal",
							"sid": 727009161259327
						}
					],
					"sid": 853111331771268
				},
				{
					"eventType": "block",
					"conditions": [
						{
							"id": "key-is-down",
							"objectClass": "Keyboard",
							"sid": 553025195528564,
							"parameters": {
								"key": 38
							}
						},
						{
							"id": "compare-instance-variable",
							"objectClass": "player",
							"sid": 908878569784631,
							"disabled": true,
							"parameters": {
								"instance-variable": "direction",
								"comparison": 0,
								"value": "1"
							}
						},
						{
							"id": "is-boolean-instance-variable-set",
							"objectClass": "player",
							"sid": 405390478072788,
							"parameters": {
								"instance-variable": "isDashing"
							},
							"isInverted": true
						}
					],
					"actions": [
						{
							"callFunction": "toDashing",
							"sid": 451366614510141
						},
						{
							"id": "set-vector-y",
							"objectClass": "player",
							"sid": 554535922874249,
							"behaviorType": "Platform",
							"parameters": {
								"vector-y": "-player.dashSpeed*0.85"
							}
						},
						{
							"id": "wait",
							"objectClass": "System",
							"sid": 992163478516560,
							"parameters": {
								"seconds": "0.3"
							}
						},
						{
							"callFunction": "toNormal",
							"sid": 180921280109277
						}
					],
					"sid": 515464365856892
				},
				{
					"eventType": "block",
					"conditions": [
						{
							"id": "key-is-down",
							"objectClass": "Keyboard",
							"sid": 502608141052652,
							"parameters": {
								"key": 40
							}
						},
						{
							"id": "compare-instance-variable",
							"objectClass": "player",
							"sid": 851044293705583,
							"disabled": true,
							"parameters": {
								"instance-variable": "direction",
								"comparison": 0,
								"value": "3"
							}
						},
						{
							"id": "is-boolean-instance-variable-set",
							"objectClass": "player",
							"sid": 759168447111177,
							"parameters": {
								"instance-variable": "isDashing"
							},
							"isInverted": true
						}
					],
					"actions": [
						{
							"callFunction": "toDashing",
							"sid": 284789082707845
						},
						{
							"id": "set-vector-y",
							"objectClass": "player",
							"sid": 946586252204169,
							"behaviorType": "Platform",
							"parameters": {
								"vector-y": "player.dashSpeed"
							}
						},
						{
							"id": "wait",
							"objectClass": "System",
							"sid": 363876772562593,
							"parameters": {
								"seconds": "0.3"
							}
						},
						{
							"callFunction": "toNormal",
							"sid": 611399386274733
						}
					],
					"sid": 130199272073738
				}
			]
		},
		{
			"eventType": "block",
			"conditions": [
				{
					"id": "on-key-pressed",
					"objectClass": "Keyboard",
					"sid": 744763384985366,
					"parameters": {
						"key": 39
					}
				}
			],
			"actions": [
				{
					"id": "simulate-control",
					"objectClass": "player",
					"sid": 812657988105234,
					"behaviorType": "Platform",
					"parameters": {
						"control": "right"
					}
				},
				{
					"id": "set-instvar-value",
					"objectClass": "player",
					"sid": 391862778628492,
					"parameters": {
						"instance-variable": "direction",
						"value": "2"
					}
				},
				{
					"id": "set-mirrored",
					"objectClass": "player",
					"sid": 322543844736431,
					"parameters": {
						"state": "not-mirrored"
					}
				}
			],
			"sid": 973030455336523
		},
		{
			"eventType": "block",
			"conditions": [
				{
					"id": "on-key-pressed",
					"objectClass": "Keyboard",
					"sid": 905167712605571,
					"parameters": {
						"key": 37
					}
				}
			],
			"actions": [
				{
					"id": "simulate-control",
					"objectClass": "player",
					"sid": 902303810549061,
					"behaviorType": "Platform",
					"parameters": {
						"control": "left"
					}
				},
				{
					"id": "set-instvar-value",
					"objectClass": "player",
					"sid": 521890949652382,
					"parameters": {
						"instance-variable": "direction",
						"value": "0"
					}
				},
				{
					"id": "set-mirrored",
					"objectClass": "player",
					"sid": 552610086315282,
					"parameters": {
						"state": "mirrored"
					}
				}
			],
			"sid": 601668706057084
		},
		{
			"eventType": "block",
			"conditions": [
				{
					"id": "every-tick",
					"objectClass": "System",
					"sid": 345074154141286
				}
			],
			"actions": [],
			"sid": 608873425908059,
			"children": [
				{
					"eventType": "block",
					"conditions": [
						{
							"id": "is-boolean-instance-variable-set",
							"objectClass": "player",
							"sid": 577870699589644,
							"parameters": {
								"instance-variable": "DashCDforShadow"
							}
						},
						{
							"id": "compare-instance-variable",
							"objectClass": "player",
							"sid": 486531919878769,
							"parameters": {
								"instance-variable": "direction",
								"comparison": 0,
								"value": "0"
							}
						}
					],
					"actions": [
						{
							"id": "set-mirrored",
							"objectClass": "player2",
							"sid": 958293067675765,
							"parameters": {
								"state": "mirrored"
							}
						}
					],
					"sid": 783702953814692
				},
				{
					"eventType": "block",
					"conditions": [
						{
							"id": "is-boolean-instance-variable-set",
							"objectClass": "player",
							"sid": 268602382949484,
							"parameters": {
								"instance-variable": "DashCDforShadow"
							}
						},
						{
							"id": "compare-instance-variable",
							"objectClass": "player",
							"sid": 798300272887224,
							"parameters": {
								"instance-variable": "direction",
								"comparison": 0,
								"value": "2"
							}
						}
					],
					"actions": [
						{
							"id": "set-mirrored",
							"objectClass": "player2",
							"sid": 842152927366734,
							"parameters": {
								"state": "not-mirrored"
							}
						}
					],
					"sid": 242972414502618
				}
			]
		},
		{
			"eventType": "block",
			"conditions": [
				{
					"id": "key-is-down",
					"objectClass": "Keyboard",
					"sid": 476625998903540,
					"parameters": {
						"key": 39
					}
				}
			],
			"actions": [
				{
					"id": "simulate-control",
					"objectClass": "player",
					"sid": 768132284500501,
					"behaviorType": "Platform",
					"parameters": {
						"control": "right"
					}
				},
				{
					"id": "set-animation",
					"objectClass": "player",
					"sid": 320601141111621,
					"parameters": {
						"animation": "\"Run\"",
						"from": "beginning"
					}
				}
			],
			"sid": 404912875374471,
			"children": [
				{
					"eventType": "block",
					"conditions": [
						{
							"id": "is-boolean-instance-variable-set",
							"objectClass": "player",
							"sid": 569670864293978,
							"parameters": {
								"instance-variable": "isDashing"
							}
						}
					],
					"actions": [
						{
							"id": "set-animation",
							"objectClass": "player2",
							"sid": 175606906209608,
							"parameters": {
								"animation": "\"Run\"",
								"from": "beginning"
							}
						}
					],
					"sid": 163566260792842
				}
			]
		},
		{
			"eventType": "block",
			"conditions": [
				{
					"id": "on-key-released",
					"objectClass": "Keyboard",
					"sid": 322302697038828,
					"parameters": {
						"key": 39
					}
				}
			],
			"actions": [
				{
					"id": "set-animation",
					"objectClass": "player",
					"sid": 550218659315973,
					"parameters": {
						"animation": "\"Idle\"",
						"from": "beginning"
					}
				}
			],
			"sid": 865292594964750,
			"children": [
				{
					"eventType": "block",
					"conditions": [
						{
							"id": "is-boolean-instance-variable-set",
							"objectClass": "player",
							"sid": 643557004476048,
							"parameters": {
								"instance-variable": "isDashing"
							}
						}
					],
					"actions": [
						{
							"id": "set-animation",
							"objectClass": "player2",
							"sid": 566476610426544,
							"parameters": {
								"animation": "\"Idle\"",
								"from": "beginning"
							}
						}
					],
					"sid": 776664177062919,
					"disabled": true
				}
			]
		},
		{
			"eventType": "block",
			"conditions": [
				{
					"id": "key-is-down",
					"objectClass": "Keyboard",
					"sid": 485205274190163,
					"parameters": {
						"key": 37
					}
				}
			],
			"actions": [
				{
					"id": "simulate-control",
					"objectClass": "player",
					"sid": 300211295906604,
					"behaviorType": "Platform",
					"parameters": {
						"control": "left"
					}
				},
				{
					"id": "set-animation",
					"objectClass": "player",
					"sid": 841681825224361,
					"parameters": {
						"animation": "\"Run\"",
						"from": "beginning"
					}
				}
			],
			"sid": 614398411691610,
			"children": [
				{
					"eventType": "block",
					"conditions": [
						{
							"id": "is-boolean-instance-variable-set",
							"objectClass": "player",
							"sid": 405675749926803,
							"parameters": {
								"instance-variable": "isDashing"
							}
						}
					],
					"actions": [
						{
							"id": "set-animation",
							"objectClass": "player2",
							"sid": 272483913980404,
							"parameters": {
								"animation": "\"Run\"",
								"from": "beginning"
							}
						}
					],
					"sid": 702860804805413
				}
			]
		},
		{
			"eventType": "block",
			"conditions": [
				{
					"id": "on-key-released",
					"objectClass": "Keyboard",
					"sid": 873130224483712,
					"parameters": {
						"key": 37
					}
				}
			],
			"actions": [
				{
					"id": "set-animation",
					"objectClass": "player",
					"sid": 522972617309519,
					"parameters": {
						"animation": "\"Idle\"",
						"from": "beginning"
					}
				},
				{
					"id": "set-animation",
					"objectClass": "player2",
					"sid": 729933295337448,
					"disabled": true,
					"parameters": {
						"animation": "\"Idle\"",
						"from": "beginning"
					}
				}
			],
			"sid": 370308253308419
		},
		{
			"eventType": "block",
			"conditions": [
				{
					"id": "on-key-pressed",
					"objectClass": "Keyboard",
					"sid": 865648610972810,
					"parameters": {
						"key": 90
					}
				}
			],
			"actions": [
				{
					"id": "simulate-control",
					"objectClass": "player",
					"sid": 179837654605010,
					"behaviorType": "Platform",
					"parameters": {
						"control": "jump"
					}
				},
				{
					"id": "play",
					"objectClass": "Audio",
					"sid": 809404791068204,
					"parameters": {
						"audio-file": "sounds_quick-jump",
						"loop": "not-looping",
						"volume": "-10",
						"tag-optional": "\"\""
					}
				}
			],
			"sid": 316031902523044,
			"disabled": true
		},
		{
			"eventType": "block",
			"conditions": [
				{
					"id": "on-key-pressed",
					"objectClass": "Keyboard",
					"sid": 125562230068843,
					"parameters": {
						"key": 38
					}
				}
			],
			"actions": [
				{
					"id": "set-instvar-value",
					"objectClass": "player",
					"sid": 668914379711437,
					"parameters": {
						"instance-variable": "direction",
						"value": "1"
					}
				},
				{
					"id": "set-angle",
					"objectClass": "player",
					"sid": 644616251513005,
					"disabled": true,
					"parameters": {
						"angle": "270"
					}
				}
			],
			"sid": 328578674526831,
			"children": [
				{
					"eventType": "block",
					"conditions": [
						{
							"id": "key-is-down",
							"objectClass": "Keyboard",
							"sid": 257703534773118,
							"parameters": {
								"key": 38
							}
						}
					],
					"actions": [],
					"sid": 845128754122097,
					"disabled": true
				}
			]
		},
		{
			"eventType": "block",
			"conditions": [
				{
					"id": "on-key-pressed",
					"objectClass": "Keyboard",
					"sid": 582150536404717,
					"parameters": {
						"key": 40
					}
				}
			],
			"actions": [
				{
					"id": "set-instvar-value",
					"objectClass": "player",
					"sid": 270763263811445,
					"parameters": {
						"instance-variable": "direction",
						"value": "3"
					}
				},
				{
					"id": "set-angle",
					"objectClass": "player",
					"sid": 407368941973796,
					"disabled": true,
					"parameters": {
						"angle": "90"
					}
				}
			],
			"sid": 704051395339004
		},
		{
			"functionName": "toDashing",
			"functionDescription": "",
			"functionCategory": "",
			"functionReturnType": "none",
			"functionIsAsync": false,
			"functionParameters": [],
			"eventType": "function-block",
			"conditions": [],
			"actions": [
				{
					"id": "play",
					"objectClass": "Audio",
					"sid": 301590520389367,
					"parameters": {
						"audio-file": "sounds_dash",
						"loop": "not-looping",
						"volume": "-10",
						"tag-optional": "\"\""
					}
				},
				{
					"id": "set-boolean-instvar",
					"objectClass": "player",
					"sid": 930861324073557,
					"parameters": {
						"instance-variable": "isDashing",
						"value": "true"
					}
				},
				{
					"id": "set-boolean-instvar",
					"objectClass": "player",
					"sid": 753324578478949,
					"parameters": {
						"instance-variable": "DashCDforShadow",
						"value": "true"
					}
				},
				{
					"id": "set-max-speed",
					"objectClass": "player",
					"sid": 839194405699222,
					"behaviorType": "Platform",
					"parameters": {
						"max-speed": "player.Platform.MaxSpeed * player.speedMulti"
					}
				},
				{
					"id": "set-max-fall-speed",
					"objectClass": "player",
					"sid": 596928635243103,
					"behaviorType": "Platform",
					"parameters": {
						"max-fall-speed": "0"
					}
				},
				{
					"id": "set-gravity",
					"objectClass": "player",
					"sid": 374646173094580,
					"disabled": true,
					"behaviorType": "Platform",
					"parameters": {
						"gravity": "0"
					}
				},
				{
					"id": "set-deceleration",
					"objectClass": "player",
					"sid": 189307622602087,
					"behaviorType": "Platform",
					"parameters": {
						"deceleration": "0"
					}
				},
				{
					"id": "set-animation",
					"objectClass": "player",
					"sid": 548683231259688,
					"parameters": {
						"animation": "\"Animation 2\"",
						"from": "beginning"
					}
				},
				{
					"id": "wait",
					"objectClass": "System",
					"sid": 678380214508019,
					"parameters": {
						"seconds": "0.075"
					}
				},
				{
					"id": "spawn-another-object",
					"objectClass": "player",
					"sid": 622207844749428,
					"parameters": {
						"object": "player2",
						"layer": "1",
						"image-point": "0",
						"create-hierarchy": false
					}
				},
				{
					"id": "wait",
					"objectClass": "System",
					"sid": 902424931624787,
					"parameters": {
						"seconds": "0.075"
					}
				},
				{
					"id": "spawn-another-object",
					"objectClass": "player",
					"sid": 782488201446739,
					"parameters": {
						"object": "player2",
						"layer": "1",
						"image-point": "0",
						"create-hierarchy": false
					}
				},
				{
					"id": "wait",
					"objectClass": "System",
					"sid": 666711674631646,
					"parameters": {
						"seconds": "0.075"
					}
				},
				{
					"id": "spawn-another-object",
					"objectClass": "player",
					"sid": 760033125931083,
					"parameters": {
						"object": "player2",
						"layer": "1",
						"image-point": "0",
						"create-hierarchy": false
					}
				}
			],
			"sid": 698300264102488
		},
		{
			"functionName": "toNormal",
			"functionDescription": "",
			"functionCategory": "",
			"functionReturnType": "none",
			"functionIsAsync": false,
			"functionParameters": [],
			"eventType": "function-block",
			"conditions": [],
			"actions": [
				{
					"id": "set-max-speed",
					"objectClass": "player",
					"sid": 427942504983520,
					"behaviorType": "Platform",
					"parameters": {
						"max-speed": "player.Platform.MaxSpeed / player.speedMulti"
					}
				},
				{
					"id": "set-gravity",
					"objectClass": "player",
					"sid": 313286249330222,
					"behaviorType": "Platform",
					"parameters": {
						"gravity": "player.normGrav"
					}
				},
				{
					"id": "set-max-fall-speed",
					"objectClass": "player",
					"sid": 693132813284524,
					"behaviorType": "Platform",
					"parameters": {
						"max-fall-speed": "1000"
					}
				},
				{
					"id": "set-deceleration",
					"objectClass": "player",
					"sid": 948241228795993,
					"behaviorType": "Platform",
					"parameters": {
						"deceleration": "player.normGrav"
					}
				},
				{
					"id": "set-animation",
					"objectClass": "player",
					"sid": 115892732944334,
					"parameters": {
						"animation": "\"Animation 1\"",
						"from": "beginning"
					}
				},
				{
					"id": "set-boolean-instvar",
					"objectClass": "player",
					"sid": 344482044028474,
					"parameters": {
						"instance-variable": "DashCDforShadow",
						"value": "false"
					}
				},
				{
					"id": "wait",
					"objectClass": "System",
					"sid": 488170762043351,
					"parameters": {
						"seconds": "0.15"
					}
				},
				{
					"id": "play",
					"objectClass": "Audio",
					"sid": 232286026766514,
					"parameters": {
						"audio-file": "sounds_quick-jump",
						"loop": "not-looping",
						"volume": "-10",
						"tag-optional": "\"\""
					}
				},
				{
					"id": "set-boolean-instvar",
					"objectClass": "player",
					"sid": 582738519605292,
					"parameters": {
						"instance-variable": "isDashing",
						"value": "false"
					}
				}
			],
			"sid": 385344740268792
		},
		{
			"eventType": "block",
			"conditions": [
				{
					"id": "is-overlapping-another-object",
					"objectClass": "player",
					"sid": 456136762059614,
					"parameters": {
						"object": "Spike"
					}
				}
			],
			"actions": [
				{
					"callFunction": "respawn",
					"sid": 582370077942739
				},
				{
					"id": "restart-layout",
					"objectClass": "System",
					"sid": 352997933863434,
					"disabled": true
				}
			],
			"sid": 846901072795453
		},
		{
			"eventType": "block",
			"conditions": [
				{
					"id": "on-start-of-layout",
					"objectClass": "System",
					"sid": 206149146016406
				}
			],
			"actions": [
				{
					"id": "set-speed",
					"objectClass": "HorizontalMovingSpikes",
					"sid": 460294356554138,
					"behaviorType": "Custom",
					"parameters": {
						"which": "vertical",
						"speed": "200"
					}
				},
				{
					"id": "set-angle-of-motion",
					"objectClass": "HorizontalMovingSpikes",
					"sid": 352777379109504,
					"behaviorType": "Custom",
					"parameters": {
						"angle": "180"
					}
				},
				{
					"id": "set-angle-of-motion",
					"objectClass": "VerticalMovingSpikes",
					"sid": 628000226069637,
					"behaviorType": "Custom",
					"parameters": {
						"angle": "0"
					}
				},
				{
					"id": "set-speed",
					"objectClass": "VerticalMovingSpikes",
					"sid": 401915237930972,
					"behaviorType": "Custom",
					"parameters": {
						"which": "vertical",
						"speed": "200"
					}
				}
			],
			"sid": 913282824405373
		},
		{
			"eventType": "block",
			"conditions": [
				{
					"id": "on-collision-with-another-object",
					"objectClass": "HorizontalMovingSpikes",
					"sid": 950610708788273,
					"parameters": {
						"object": "PlatformStopper180"
					}
				}
			],
			"actions": [
				{
					"id": "set-angle-of-motion",
					"objectClass": "HorizontalMovingSpikes",
					"sid": 338645090477945,
					"behaviorType": "Custom",
					"parameters": {
						"angle": "180"
					}
				}
			],
			"sid": 693448384983401
		},
		{
			"eventType": "block",
			"conditions": [
				{
					"id": "on-collision-with-another-object",
					"objectClass": "HorizontalMovingSpikes",
					"sid": 334073197983849,
					"parameters": {
						"object": "PlatformStopper360"
					}
				}
			],
			"actions": [
				{
					"id": "set-angle-of-motion",
					"objectClass": "HorizontalMovingSpikes",
					"sid": 343859545006548,
					"behaviorType": "Custom",
					"parameters": {
						"angle": "360"
					}
				}
			],
			"sid": 881246930884904
		},
		{
			"eventType": "block",
			"conditions": [
				{
					"id": "is-overlapping-another-object",
					"objectClass": "player",
					"sid": 313343291371656,
					"parameters": {
						"object": "Exit"
					}
				}
			],
			"actions": [
				{
					"id": "go-to-nextprevious-layout",
					"objectClass": "System",
					"sid": 540266939383552,
					"parameters": {
						"which": "next"
					}
				}
			],
			"sid": 161398831436330
		},
		{
			"eventType": "block",
			"conditions": [
				{
					"id": "is-overlapping-another-object",
					"objectClass": "player",
					"sid": 375331808767760,
					"parameters": {
						"object": "HorizontalMovingSpikes"
					}
				}
			],
			"actions": [
				{
					"callFunction": "respawn",
					"sid": 883378163189127
				},
				{
					"id": "restart-layout",
					"objectClass": "System",
					"sid": 145001557341022,
					"disabled": true
				}
			],
			"sid": 761404837919784
		},
		{
			"eventType": "block",
			"conditions": [
				{
					"id": "on-collision-with-another-object",
					"objectClass": "player",
					"sid": 211039868206731,
					"parameters": {
						"object": "Sprite"
					}
				}
			],
			"actions": [
				{
					"id": "set-position",
					"objectClass": "player",
					"sid": 896062025225975,
					"disabled": true,
					"parameters": {
						"x": "1721",
						"y": "1254"
					}
				},
				{
					"id": "go-to-nextprevious-layout",
					"objectClass": "System",
					"sid": 155060036868160,
					"parameters": {
						"which": "next"
					}
				}
			],
			"sid": 653030331112843
		},
		{
			"eventType": "block",
			"conditions": [
				{
					"id": "on-start-of-layout",
					"objectClass": "System",
					"sid": 151865035818728
				}
			],
			"actions": [
				{
					"id": "add-child",
					"objectClass": "player",
					"sid": 489886518524892,
					"parameters": {
						"child": "Sprite3",
						"transform-x": true,
						"transform-y": true,
						"transform-w": false,
						"transform-h": false,
						"transform-a": true,
						"transform-z-elevation": true,
						"destroy-with-parent": true
					}
				}
			],
			"sid": 667590128860325
		},
		{
			"eventType": "block",
			"conditions": [
				{
					"id": "on-key-pressed",
					"objectClass": "Keyboard",
					"sid": 163564362347749,
					"parameters": {
						"key": 49
					}
				}
			],
			"actions": [
				{
					"id": "go-to-layout",
					"objectClass": "System",
					"sid": 433755559090455,
					"parameters": {
						"layout": "Layout 1"
					}
				}
			],
			"sid": 684162579305713,
			"disabled": true
		},
		{
			"eventType": "block",
			"conditions": [
				{
					"id": "on-key-pressed",
					"objectClass": "Keyboard",
					"sid": 976048496753099,
					"parameters": {
						"key": 50
					}
				}
			],
			"actions": [
				{
					"id": "go-to-layout",
					"objectClass": "System",
					"sid": 877921801809603,
					"parameters": {
						"layout": "Layout 2"
					}
				}
			],
			"sid": 483734486102134,
			"disabled": true
		},
		{
			"eventType": "block",
			"conditions": [
				{
					"id": "on-created",
					"objectClass": "player2",
					"sid": 814709050973447
				},
				{
					"id": "pick-by-comparison",
					"objectClass": "System",
					"sid": 462159692121415,
					"parameters": {
						"object": "player2",
						"expression": "player2.UID",
						"comparison": 4,
						"value": "6"
					}
				}
			],
			"actions": [
				{
					"id": "start-fade",
					"objectClass": "player2",
					"sid": 257366338320019,
					"behaviorType": "Fade"
				},
				{
					"id": "set-enabled",
					"objectClass": "player2",
					"sid": 211886912911645,
					"behaviorType": "ScrollTo",
					"parameters": {
						"state": "disabled"
					}
				},
				{
					"id": "set-enabled",
					"objectClass": "player2",
					"sid": 970875566504107,
					"behaviorType": "Platform",
					"parameters": {
						"state": "disabled"
					}
				}
			],
			"sid": 733648709141622
		},
		{
			"eventType": "block",
			"conditions": [
				{
					"id": "every-tick",
					"objectClass": "System",
					"sid": 538236724846988
				}
			],
			"actions": [
				{
					"id": "set-position",
					"objectClass": "Camera",
					"sid": 200876910778002,
					"parameters": {
						"x": "lerp(Self.X,player.X,0.1)",
						"y": "lerp(Self.y,player.y,0.1)"
					}
				}
			],
			"sid": 436674465165080
		},
		{
			"eventType": "block",
			"conditions": [
				{
					"id": "on-start-of-layout",
					"objectClass": "System",
					"sid": 147105148196272
				}
			],
			"actions": [
				{
					"id": "set-visible",
					"objectClass": "Zoomtrigger1",
					"sid": 936545325869534,
					"parameters": {
						"visibility": "invisible"
					}
				},
				{
					"id": "set-visible",
					"objectClass": "Zoomtrigger2",
					"sid": 838317804745961,
					"parameters": {
						"visibility": "invisible"
					}
				}
			],
			"sid": 371750754255261
		},
		{
			"eventType": "block",
			"conditions": [
				{
					"id": "compare-eventvar",
					"objectClass": "System",
					"sid": 207465858074441,
					"parameters": {
						"variable": "current_zoom",
						"comparison": 2,
						"value": "target"
					}
				}
			],
			"actions": [],
			"sid": 703442759098750,
			"children": [
				{
					"eventType": "block",
					"conditions": [
						{
							"id": "every-x-seconds",
							"objectClass": "System",
							"sid": 285317521605977,
							"parameters": {
								"interval-seconds": "0.01"
							}
						}
					],
					"actions": [
						{
							"id": "add-to-eventvar",
							"objectClass": "System",
							"sid": 148610686429944,
							"parameters": {
								"variable": "current_zoom",
								"value": "0.01"
							}
						},
						{
							"id": "set-layout-scale",
							"objectClass": "System",
							"sid": 689250067138032,
							"parameters": {
								"scale": "current_zoom"
							}
						}
					],
					"sid": 632084307749508
				}
			]
		},
		{
			"eventType": "block",
			"conditions": [
				{
					"id": "compare-eventvar",
					"objectClass": "System",
					"sid": 981336680624370,
					"parameters": {
						"variable": "current_zoom",
						"comparison": 4,
						"value": "target"
					}
				}
			],
			"actions": [],
			"sid": 377222420457015,
			"children": [
				{
					"eventType": "block",
					"conditions": [
						{
							"id": "every-x-seconds",
							"objectClass": "System",
							"sid": 924952415711333,
							"parameters": {
								"interval-seconds": "0.01"
							}
						}
					],
					"actions": [
						{
							"id": "subtract-from-eventvar",
							"objectClass": "System",
							"sid": 581405287757946,
							"parameters": {
								"variable": "current_zoom",
								"value": "0.01"
							}
						},
						{
							"id": "set-layout-scale",
							"objectClass": "System",
							"sid": 709481303559739,
							"parameters": {
								"scale": "current_zoom"
							}
						}
					],
					"sid": 254986306637753
				}
			]
		},
		{
			"eventType": "block",
			"conditions": [
				{
					"id": "is-overlapping-another-object",
					"objectClass": "player",
					"sid": 112244933829052,
					"parameters": {
						"object": "Zoomtrigger2"
					},
					"isInverted": true
				},
				{
					"id": "is-overlapping-another-object",
					"objectClass": "player",
					"sid": 913555173398803,
					"parameters": {
						"object": "Zoomtrigger1"
					},
					"isInverted": true
				}
			],
			"actions": [
				{
					"id": "set-eventvar-value",
					"objectClass": "System",
					"sid": 123704534989240,
					"parameters": {
						"variable": "target",
						"value": "1"
					}
				}
			],
			"sid": 387866071465295
		},
		{
			"eventType": "block",
			"conditions": [
				{
					"id": "is-overlapping-another-object",
					"objectClass": "player",
					"sid": 481814510449099,
					"parameters": {
						"object": "Zoomtrigger1"
					}
				}
			],
			"actions": [
				{
					"id": "set-eventvar-value",
					"objectClass": "System",
					"sid": 809484749185185,
					"parameters": {
						"variable": "target",
						"value": "Zoomtrigger1.zoomtrigger"
					}
				}
			],
			"sid": 498586704639564
		},
		{
			"eventType": "block",
			"conditions": [
				{
					"id": "is-overlapping-another-object",
					"objectClass": "player",
					"sid": 316676131442654,
					"parameters": {
						"object": "Zoomtrigger2"
					}
				}
			],
			"actions": [
				{
					"id": "set-eventvar-value",
					"objectClass": "System",
					"sid": 609529350704673,
					"parameters": {
						"variable": "target",
						"value": "Zoomtrigger2.zoomtarget2"
					}
				}
			],
			"sid": 240598121638518
		},
		{
			"eventType": "block",
			"conditions": [
				{
					"id": "on-collision-with-another-object",
					"objectClass": "player",
					"sid": 317945967872063,
					"parameters": {
						"object": "waterDeathbox"
					}
				}
			],
			"actions": [
				{
					"callFunction": "respawn",
					"sid": 792725647592675
				}
			],
			"sid": 979327483686738
		},
		{
			"eventType": "block",
			"conditions": [
				{
					"id": "on-collision-with-another-object",
					"objectClass": "VerticalMovingSpikes",
					"sid": 323359974749208,
					"parameters": {
						"object": "PlatformStopper90"
					}
				}
			],
			"actions": [
				{
					"id": "set-angle-of-motion",
					"objectClass": "VerticalMovingSpikes",
					"sid": 195105327799028,
					"behaviorType": "Custom",
					"parameters": {
						"angle": "90"
					}
				}
			],
			"sid": 305418232251754
		},
		{
			"eventType": "block",
			"conditions": [
				{
					"id": "on-collision-with-another-object",
					"objectClass": "VerticalMovingSpikes",
					"sid": 733743590101499,
					"parameters": {
						"object": "PlatformStopper270"
					}
				}
			],
			"actions": [
				{
					"id": "set-angle-of-motion",
					"objectClass": "VerticalMovingSpikes",
					"sid": 407020504110755,
					"behaviorType": "Custom",
					"parameters": {
						"angle": "270"
					}
				}
			],
			"sid": 407909484792446
		},
		{
			"eventType": "block",
			"conditions": [
				{
					"id": "is-overlapping-another-object",
					"objectClass": "player",
					"sid": 909886963736906,
					"parameters": {
						"object": "VerticalMovingSpikes"
					}
				}
			],
			"actions": [
				{
					"callFunction": "respawn",
					"sid": 906732427767813
				},
				{
					"id": "restart-layout",
					"objectClass": "System",
					"sid": 854435621291102,
					"disabled": true
				}
			],
			"sid": 698209532040362
		},
		{
			"eventType": "block",
			"conditions": [
				{
					"id": "on-collision-with-another-object",
					"objectClass": "player",
					"sid": 547748326945505,
					"parameters": {
						"object": "checkpointHitBox"
					}
				}
			],
			"actions": [
				{
					"id": "set-instvar-value",
					"objectClass": "player",
					"sid": 933899239661002,
					"parameters": {
						"instance-variable": "checkpointX",
						"value": "checkpointHitBox.ImagePointX(\"1\")"
					}
				},
				{
					"id": "set-instvar-value",
					"objectClass": "player",
					"sid": 115906749802212,
					"parameters": {
						"instance-variable": "checkpointY",
						"value": "checkpointHitBox.ImagePointY(\"1\")"
					}
				}
			],
			"sid": 201730076784234
		},
		{
			"eventType": "block",
			"conditions": [
				{
					"id": "on-start-of-layout",
					"objectClass": "System",
					"sid": 747519057616556
				}
			],
			"actions": [
				{
					"id": "set-instvar-value",
					"objectClass": "player",
					"sid": 580183530038712,
					"parameters": {
						"instance-variable": "checkpointX",
						"value": "player.X"
					}
				},
				{
					"id": "set-instvar-value",
					"objectClass": "player",
					"sid": 546227358358635,
					"parameters": {
						"instance-variable": "checkpointY",
						"value": "player.Y"
					}
				}
			],
			"sid": 757387152305716
		},
		{
			"functionName": "respawn",
			"functionDescription": "",
			"functionCategory": "",
			"functionReturnType": "none",
			"functionIsAsync": false,
			"functionParameters": [],
			"eventType": "function-block",
			"conditions": [],
			"actions": [
				{
					"id": "play",
					"objectClass": "Audio",
					"sid": 529766072879202,
					"parameters": {
						"audio-file": "deathSound",
						"loop": "not-looping",
						"volume": "-10",
						"tag-optional": "\"\""
					}
				},
				{
					"id": "set-position",
					"objectClass": "player",
					"sid": 609801006988267,
					"parameters": {
						"x": "player.checkpointX",
						"y": "player.checkpointY"
					}
				},
				{
					"id": "set-vector-x",
					"objectClass": "player",
					"sid": 134336568992543,
					"behaviorType": "Platform",
					"parameters": {
						"vector-x": "0"
					}
				},
				{
					"id": "set-vector-y",
					"objectClass": "player",
					"sid": 392345003745253,
					"behaviorType": "Platform",
					"parameters": {
						"vector-y": "0"
					}
				}
			],
			"sid": 545379422917300
		},
		{
			"eventType": "block",
			"conditions": [
				{
					"id": "on-start-of-layout",
					"objectClass": "System",
					"sid": 789883388660452
				},
				{
					"id": "compare-two-values",
					"objectClass": "System",
					"sid": 361472837519359,
					"parameters": {
						"first-value": "LayoutName",
						"comparison": 0,
						"second-value": "\"Layout 1\""
					}
				}
			],
			"actions": [
				{
					"id": "play",
					"objectClass": "Audio",
					"sid": 366364257003313,
					"parameters": {
						"audio-file": "backgroundSound",
						"loop": "looping",
						"volume": "-20",
						"tag-optional": "\"\""
					}
				}
			],
			"sid": 201401448300626
		}
	],
	"sid": 325422612367472
}