{
	"name": "player2",
	"plugin-id": "Sprite",
	"sid": 534996170992031,
	"isGlobal": false,
	"instanceVariables": [
		{
			"name": "right",
			"type": "boolean",
			"desc": "",
			"sid": 387732081227736
		},
		{
			"name": "normGrav",
			"type": "number",
			"desc": "",
			"sid": 146478342312114
		},
		{
			"name": "speedMulti",
			"type": "number",
			"desc": "",
			"sid": 301205127865266
		},
		{
			"name": "dashSpeed",
			"type": "number",
			"desc": "",
			"sid": 763346152639209
		},
		{
			"name": "isDashing",
			"type": "boolean",
			"desc": "",
			"sid": 905925484473022
		},
		{
			"name": "direction",
			"type": "number",
			"desc": "0 - left, 1 - up, 2 - right, 3 - down",
			"sid": 952231077140090
		}
	],
	"behaviorTypes": [
		{
			"behaviorId": "Platform",
			"name": "Platform",
			"sid": 918163024039761
		},
		{
			"behaviorId": "scrollto",
			"name": "ScrollTo",
			"sid": 478682708179274
		},
		{
			"behaviorId": "bound",
			"name": "BoundToLayout",
			"sid": 511417213261393
		},
		{
			"behaviorId": "Fade",
			"name": "Fade",
			"sid": 813932672659072
		}
	],
	"effectTypes": [],
	"animations": {
		"items": [
			{
				"frames": [
					{
						"width": 21,
						"height": 19,
						"originX": 0.47619047619047616,
						"originY": 0.5263157894736842,
						"originalSource": "",
						"exportFormat": "png",
						"exportQuality": 0.8,
						"imageSpriteId": 9850159,
						"collisionPoly": {
							"points": [
								0.38095238095238093,
								1,
								0.6190476190476192,
								1,
								0.6190476190476192,
								0.05263157894736842,
								0.38095238095238093,
								0.05263157894736842
							]
						},
						"useCollisionPoly": true,
						"duration": 2
					},
					{
						"width": 21,
						"height": 19,
						"originX": 0.47619047619047616,
						"originY": 0.5263157894736842,
						"originalSource": "",
						"exportFormat": "png",
						"exportQuality": 0.8,
						"imageSpriteId": 6310393,
						"collisionPoly": {
							"points": [
								0.38095238095238093,
								1,
								0.6190476190476192,
								1,
								0.6190476190476192,
								0.05263157894736842,
								0.38095238095238093,
								0.05263157894736842
							]
						},
						"useCollisionPoly": true,
						"duration": 2
					},
					{
						"width": 21,
						"height": 19,
						"originX": 0.47619047619047616,
						"originY": 0.5263157894736842,
						"originalSource": "",
						"exportFormat": "png",
						"exportQuality": 0.8,
						"imageSpriteId": 8368185,
						"collisionPoly": {
							"points": [
								0.38095238095238093,
								1,
								0.6190476190476192,
								1,
								0.6190476190476192,
								0.05263157894736842,
								0.38095238095238093,
								0.05263157894736842
							]
						},
						"useCollisionPoly": true,
						"duration": 2
					}
				],
				"sid": 517563733405300,
				"name": "Idle",
				"isLooping": true,
				"isPingPong": false,
				"repeatCount": 1,
				"repeatTo": 0,
				"speed": 5
			},
			{
				"frames": [
					{
						"width": 17,
						"height": 19,
						"originX": 0.5,
						"originY": 0.5,
						"originalSource": "",
						"exportFormat": "png",
						"exportQuality": 0.8,
						"imageSpriteId": 7934784,
						"collisionPoly": {
							"points": [
								0.4117647058823529,
								0.3684210526315789,
								0.5,
								0.3157894736842105,
								0.8823529411764706,
								0.05263157894736842,
								0.9411764705882353,
								0.5,
								0.7647058823529411,
								0.7894736842105263,
								0.5,
								0.9473684210526315,
								0.29411764705882354,
								0.6842105263157895,
								0.17647058823529413,
								0.5
							]
						},
						"useCollisionPoly": true,
						"duration": 1
					},
					{
						"width": 17,
						"height": 19,
						"originX": 0.5,
						"originY": 0.5,
						"originalSource": "",
						"exportFormat": "png",
						"exportQuality": 0.8,
						"imageSpriteId": 1834805,
						"collisionPoly": {
							"points": [
								0.4117647058823529,
								0.3684210526315789,
								0.5,
								0.10526315789473684,
								0.8823529411764706,
								0.05263157894736842,
								0.8823529411764706,
								0.5,
								0.7647058823529411,
								0.7894736842105263,
								0.5,
								0.8947368421052632,
								0.23529411764705882,
								0.7368421052631579,
								0.17647058823529413,
								0.5
							]
						},
						"useCollisionPoly": true,
						"duration": 1
					},
					{
						"width": 17,
						"height": 19,
						"originX": 0.5,
						"originY": 0.5,
						"originalSource": "",
						"exportFormat": "png",
						"exportQuality": 0.8,
						"imageSpriteId": 6933004,
						"collisionPoly": {
							"points": [
								0.4117647058823529,
								0.3684210526315789,
								0.5,
								0.15789473684210525,
								0.8823529411764706,
								0.05263157894736842,
								0.9411764705882353,
								0.5,
								0.8823529411764706,
								0.8947368421052632,
								0.5,
								0.7894736842105263,
								0.23529411764705882,
								0.7368421052631579,
								0.35294117647058826,
								0.5
							]
						},
						"useCollisionPoly": true,
						"duration": 1
					},
					{
						"width": 17,
						"height": 19,
						"originX": 0.5,
						"originY": 0.5,
						"originalSource": "",
						"exportFormat": "png",
						"exportQuality": 0.8,
						"imageSpriteId": 6050623,
						"collisionPoly": {
							"points": [
								0.47058823529411764,
								0.42105263157894735,
								0.5,
								0.21052631578947367,
								0.8823529411764706,
								0.05263157894736842,
								0.8823529411764706,
								0.5,
								0.7647058823529411,
								0.7894736842105263,
								0.5,
								0.8421052631578947,
								0.23529411764705882,
								0.7368421052631579,
								0.29411764705882354,
								0.5
							]
						},
						"useCollisionPoly": true,
						"duration": 1
					},
					{
						"width": 17,
						"height": 19,
						"originX": 0.5,
						"originY": 0.5,
						"originalSource": "",
						"exportFormat": "png",
						"exportQuality": 0.8,
						"imageSpriteId": 8796090,
						"collisionPoly": {
							"points": [
								0.4117647058823529,
								0.3684210526315789,
								0.5,
								0.3157894736842105,
								0.8823529411764706,
								0.05263157894736842,
								0.9411764705882353,
								0.5,
								0.8235294117647058,
								0.8421052631578947,
								0.5,
								0.8947368421052632,
								0.35294117647058826,
								0.631578947368421,
								0.17647058823529413,
								0.5
							]
						},
						"useCollisionPoly": true,
						"duration": 1
					},
					{
						"width": 17,
						"height": 19,
						"originX": 0.5,
						"originY": 0.5,
						"originalSource": "",
						"exportFormat": "png",
						"exportQuality": 0.8,
						"imageSpriteId": 8164233,
						"collisionPoly": {
							"points": [
								0.47058823529411764,
								0.42105263157894735,
								0.5,
								0.15789473684210525,
								0.8235294117647058,
								0.10526315789473684,
								0.8823529411764706,
								0.5,
								0.7058823529411765,
								0.7368421052631579,
								0.5,
								0.8421052631578947,
								0.29411764705882354,
								0.6842105263157895,
								0.17647058823529413,
								0.5
							]
						},
						"useCollisionPoly": true,
						"duration": 1
					},
					{
						"width": 17,
						"height": 19,
						"originX": 0.5,
						"originY": 0.5,
						"originalSource": "",
						"exportFormat": "png",
						"exportQuality": 0.8,
						"imageSpriteId": 8478216,
						"collisionPoly": {
							"points": [
								0.4117647058823529,
								0.3684210526315789,
								0.5,
								0.15789473684210525,
								0.8823529411764706,
								0.05263157894736842,
								0.8823529411764706,
								0.5,
								0.8235294117647058,
								0.8421052631578947,
								0.5,
								0.7894736842105263,
								0.23529411764705882,
								0.7368421052631579,
								0.35294117647058826,
								0.5
							]
						},
						"useCollisionPoly": true,
						"duration": 1
					},
					{
						"width": 17,
						"height": 19,
						"originX": 0.5,
						"originY": 0.5,
						"originalSource": "",
						"exportFormat": "png",
						"exportQuality": 0.8,
						"imageSpriteId": 3006525,
						"collisionPoly": {
							"points": [
								0.47058823529411764,
								0.42105263157894735,
								0.5,
								0.21052631578947367,
								0.8823529411764706,
								0.05263157894736842,
								0.8823529411764706,
								0.5,
								0.7647058823529411,
								0.7894736842105263,
								0.5,
								0.8421052631578947,
								0.23529411764705882,
								0.7368421052631579,
								0.29411764705882354,
								0.5
							]
						},
						"useCollisionPoly": true,
						"duration": 1
					}
				],
				"sid": 878472414541099,
				"name": "Run",
				"isLooping": false,
				"isPingPong": false,
				"repeatCount": 1,
				"repeatTo": 0,
				"speed": 5
			},
			{
				"frames": [
					{
						"width": 17,
						"height": 19,
						"originX": 0.5,
						"originY": 0.5,
						"originalSource": "",
						"exportFormat": "png",
						"exportQuality": 0.8,
						"imageSpriteId": 5270043,
						"collisionPoly": {
							"points": [
								0.47058823529411764,
								0.42105263157894735,
								0.5,
								0.15789473684210525,
								0.7647058823529411,
								0.15789473684210525,
								0.8235294117647058,
								0.5,
								0.8823529411764706,
								0.8947368421052632,
								0.5,
								0.9473684210526315,
								0.23529411764705882,
								0.7368421052631579,
								0.35294117647058826,
								0.5
							]
						},
						"useCollisionPoly": true,
						"duration": 1
					},
					{
						"width": 17,
						"height": 19,
						"originX": 0.5,
						"originY": 0.5,
						"originalSource": "",
						"exportFormat": "png",
						"exportQuality": 0.8,
						"imageSpriteId": 5808445,
						"collisionPoly": {
							"points": [
								0.47058823529411764,
								0.42105263157894735,
								0.5,
								0.15789473684210525,
								0.7647058823529411,
								0.15789473684210525,
								0.8235294117647058,
								0.5,
								0.8823529411764706,
								0.8947368421052632,
								0.5,
								0.9473684210526315,
								0.35294117647058826,
								0.631578947368421,
								0.35294117647058826,
								0.5
							]
						},
						"useCollisionPoly": true,
						"duration": 1
					},
					{
						"width": 17,
						"height": 19,
						"originX": 0.5,
						"originY": 0.5,
						"originalSource": "",
						"exportFormat": "png",
						"exportQuality": 0.8,
						"imageSpriteId": 8534346,
						"collisionPoly": {
							"points": [
								0.47058823529411764,
								0.42105263157894735,
								0.5,
								0.15789473684210525,
								0.7647058823529411,
								0.15789473684210525,
								0.8235294117647058,
								0.5,
								0.8235294117647058,
								0.8421052631578947,
								0.5,
								0.9473684210526315,
								0.35294117647058826,
								0.631578947368421,
								0.35294117647058826,
								0.5
							]
						},
						"useCollisionPoly": true,
						"duration": 1
					},
					{
						"width": 17,
						"height": 19,
						"originX": 0.5,
						"originY": 0.5,
						"originalSource": "",
						"exportFormat": "png",
						"exportQuality": 0.8,
						"imageSpriteId": 8471394,
						"collisionPoly": {
							"points": [
								0.47058823529411764,
								0.42105263157894735,
								0.5,
								0.15789473684210525,
								0.7647058823529411,
								0.15789473684210525,
								0.8235294117647058,
								0.5,
								0.8823529411764706,
								0.8947368421052632,
								0.5,
								0.9473684210526315,
								0.35294117647058826,
								0.631578947368421,
								0.35294117647058826,
								0.5
							]
						},
						"useCollisionPoly": true,
						"duration": 1
					},
					{
						"width": 17,
						"height": 19,
						"originX": 0.5,
						"originY": 0.5,
						"originalSource": "",
						"exportFormat": "png",
						"exportQuality": 0.8,
						"imageSpriteId": 9701148,
						"collisionPoly": {
							"points": [
								0.47058823529411764,
								0.42105263157894735,
								0.5,
								0.15789473684210525,
								0.7647058823529411,
								0.15789473684210525,
								0.8235294117647058,
								0.5,
								0.8823529411764706,
								0.8947368421052632,
								0.5,
								0.9473684210526315,
								0.23529411764705882,
								0.7368421052631579,
								0.35294117647058826,
								0.5
							]
						},
						"useCollisionPoly": true,
						"duration": 1
					}
				],
				"sid": 920066854427988,
				"name": "DashUp",
				"isLooping": false,
				"isPingPong": false,
				"repeatCount": 1,
				"repeatTo": 0,
				"speed": 5
			}
		],
		"subfolders": []
	}
}